{
	"name": "p_Demo_Dim_Data_Ingestion_forEach",
	"properties": {
		"activities": [
			{
				"name": "ForEach1",
				"type": "ForEach",
				"dependsOn": [
					{
						"activity": "lkp_cntrl_table",
						"dependencyConditions": [
							"Succeeded"
						]
					}
				],
				"userProperties": [],
				"typeProperties": {
					"items": {
						"value": "@activity('lkp_cntrl_table').output.value",
						"type": "Expression"
					},
					"activities": [
						{
							"name": "cpy_AzureSQL_DIM_ADLS",
							"type": "Copy",
							"dependsOn": [
								{
									"activity": "lkp_Last_Max_Date",
									"dependencyConditions": [
										"Succeeded"
									]
								},
								{
									"activity": "sv_current_timestamp",
									"dependencyConditions": [
										"Succeeded"
									]
								}
							],
							"policy": {
								"timeout": "0.12:00:00",
								"retry": 0,
								"retryIntervalInSeconds": 30,
								"secureOutput": false,
								"secureInput": false
							},
							"userProperties": [],
							"typeProperties": {
								"source": {
									"type": "AzureSqlSource",
									"sqlReaderQuery": {
										"value": "SELECT\n *\nFROM @{item().SCHEMA_NAME}.@{item().TABLE_NAME}\nWHERE\n @{item().CDC_COLUMN} > '@{if(empty(item().INITIAL_LOAD_DATE),activity('lkp_Last_Max_Date').output.value[0].cdc , item().INITIAL_LOAD_DATE)}'\n\n\n ",
										"type": "Expression"
									},
									"queryTimeout": "02:00:00",
									"partitionOption": "None"
								},
								"sink": {
									"type": "ParquetSink",
									"storeSettings": {
										"type": "AzureBlobFSWriteSettings"
									},
									"formatSettings": {
										"type": "ParquetWriteSettings"
									}
								},
								"enableStaging": false,
								"translator": {
									"type": "TabularTranslator",
									"typeConversion": true,
									"typeConversionSettings": {
										"allowDataTruncation": true,
										"treatBooleanAsNumber": false
									}
								}
							},
							"inputs": [
								{
									"referenceName": "DS_SQLDB_DIM_Tables",
									"type": "DatasetReference"
								}
							],
							"outputs": [
								{
									"referenceName": "parquet_dynamci",
									"type": "DatasetReference",
									"parameters": {
										"container": "bronze",
										"folder": {
											"value": "@item().TABLE_NAME",
											"type": "Expression"
										},
										"file": {
											"value": "@concat(item().TABLE_NAME,'-',variables('curr'))",
											"type": "Expression"
										}
									}
								}
							]
						},
						{
							"name": "lkp_Last_Max_Date",
							"type": "Lookup",
							"dependsOn": [],
							"policy": {
								"timeout": "0.12:00:00",
								"retry": 0,
								"retryIntervalInSeconds": 30,
								"secureOutput": false,
								"secureInput": false
							},
							"userProperties": [],
							"typeProperties": {
								"source": {
									"type": "JsonSource",
									"storeSettings": {
										"type": "AzureBlobFSReadSettings",
										"recursive": true,
										"enablePartitionDiscovery": false
									},
									"formatSettings": {
										"type": "JsonReadSettings"
									}
								},
								"dataset": {
									"referenceName": "dynamic_json",
									"type": "DatasetReference",
									"parameters": {
										"container": "bronze",
										"folder": "cdc",
										"file": {
											"value": "@concat(item().TABLE_NAME,'_cdc.json')",
											"type": "Expression"
										}
									}
								},
								"firstRowOnly": false
							}
						},
						{
							"name": "sv_current_timestamp",
							"type": "SetVariable",
							"dependsOn": [],
							"policy": {
								"secureOutput": false,
								"secureInput": false
							},
							"userProperties": [],
							"typeProperties": {
								"variableName": "curr",
								"value": {
									"value": "@utcNow()",
									"type": "Expression"
								}
							}
						},
						{
							"name": "if_Check_empty_file",
							"type": "IfCondition",
							"dependsOn": [
								{
									"activity": "cpy_AzureSQL_DIM_ADLS",
									"dependencyConditions": [
										"Succeeded"
									]
								}
							],
							"userProperties": [],
							"typeProperties": {
								"expression": {
									"value": "@greater(activity('cpy_AzureSQL_DIM_ADLS').output.dataRead,0 )",
									"type": "Expression"
								},
								"ifFalseActivities": [
									{
										"name": "del_Empty_Files",
										"type": "Delete",
										"dependsOn": [],
										"policy": {
											"timeout": "0.12:00:00",
											"retry": 0,
											"retryIntervalInSeconds": 30,
											"secureOutput": false,
											"secureInput": false
										},
										"userProperties": [],
										"typeProperties": {
											"dataset": {
												"referenceName": "parquet_dynamci",
												"type": "DatasetReference",
												"parameters": {
													"container": "bronze",
													"folder": {
														"value": "@item().TABLE_NAME",
														"type": "Expression"
													},
													"file": {
														"value": "@concat(item().TABLE_NAME,'-',variables('curr'))",
														"type": "Expression"
													}
												}
											},
											"logStorageSettings": {
												"linkedServiceName": {
													"referenceName": "LS_AzureDataLake",
													"type": "LinkedServiceReference"
												},
												"path": "bronze/"
											},
											"enableLogging": true,
											"storeSettings": {
												"type": "AzureBlobStorageReadSettings",
												"recursive": true,
												"enablePartitionDiscovery": false
											}
										}
									}
								],
								"ifTrueActivities": [
									{
										"name": "scrpt_Pick_MAX_cdc_date",
										"type": "Script",
										"dependsOn": [],
										"policy": {
											"timeout": "0.12:00:00",
											"retry": 0,
											"retryIntervalInSeconds": 30,
											"secureOutput": false,
											"secureInput": false
										},
										"userProperties": [],
										"typeProperties": {
											"scripts": [
												{
													"type": "Query",
													"text": {
														"value": "SELECT\n MAX(@{item().CDC_COLUMN}) as cdc\nFROM @{item().SCHEMA_NAME}.@{item().TABLE_NAME}",
														"type": "Expression"
													}
												}
											],
											"scriptBlockExecutionTimeout": "02:00:00"
										}
									},
									{
										"name": "cpy_cdc_MAX_to_file",
										"type": "Copy",
										"dependsOn": [
											{
												"activity": "scrpt_Pick_MAX_cdc_date",
												"dependencyConditions": [
													"Succeeded"
												]
											}
										],
										"policy": {
											"timeout": "0.12:00:00",
											"retry": 0,
											"retryIntervalInSeconds": 30,
											"secureOutput": false,
											"secureInput": false
										},
										"userProperties": [],
										"typeProperties": {
											"source": {
												"type": "JsonSource",
												"additionalColumns": [
													{
														"name": "cdc",
														"value": {
															"value": "@activity('scrpt_Pick_MAX_cdc_date').output.resultSets[0].rows[0].cdc",
															"type": "Expression"
														}
													}
												],
												"storeSettings": {
													"type": "AzureBlobFSReadSettings",
													"recursive": true,
													"enablePartitionDiscovery": false
												},
												"formatSettings": {
													"type": "JsonReadSettings"
												}
											},
											"sink": {
												"type": "JsonSink",
												"storeSettings": {
													"type": "AzureBlobFSWriteSettings"
												},
												"formatSettings": {
													"type": "JsonWriteSettings"
												}
											},
											"enableStaging": false
										},
										"inputs": [
											{
												"referenceName": "dynamic_json",
												"type": "DatasetReference",
												"parameters": {
													"container": "bronze",
													"folder": "cdc",
													"file": "empty.json"
												}
											}
										],
										"outputs": [
											{
												"referenceName": "dynamic_json",
												"type": "DatasetReference",
												"parameters": {
													"container": "bronze",
													"folder": "cdc",
													"file": {
														"value": "@concat(item().TABLE_NAME,'_cdc.json')",
														"type": "Expression"
													}
												}
											}
										]
									}
								]
							}
						}
					]
				}
			},
			{
				"name": "lkp_cntrl_table",
				"type": "Lookup",
				"dependsOn": [],
				"policy": {
					"timeout": "0.12:00:00",
					"retry": 0,
					"retryIntervalInSeconds": 30,
					"secureOutput": false,
					"secureInput": false
				},
				"userProperties": [],
				"typeProperties": {
					"source": {
						"type": "AzureSqlSource",
						"sqlReaderQuery": "SELECT SCHEMA_NAME, TABLE_NAME, CDC_COLUMN, INITIAL_LOAD_DATE FROM [dbo].[Dim_Control_table]",
						"queryTimeout": "02:00:00",
						"partitionOption": "None"
					},
					"dataset": {
						"referenceName": "Azure_SQL_DIM_Table",
						"type": "DatasetReference"
					},
					"firstRowOnly": false
				}
			}
		],
		"variables": {
			"curr": {
				"type": "String"
			}
		},
		"annotations": []
	}
}